[{"ContainerToolsException.Message":".FileNotFoundError: [Errno 2] No such file or directory: 'C:\\\\Temp\\\\Gateway\\\\docker-compose.yml'","ContainerToolsException.ErrorCode":"DT1001","ContainerToolsException.StackTrace":"   в System.Runtime.CompilerServices.TaskAwaiter.ThrowForNonSuccess(Task task)\r\n   в System.Runtime.CompilerServices.TaskAwaiter.HandleNonSuccessAndDebuggerNotification(Task task)\r\n   в Microsoft.Docker.DockerComposeClient.<ExecuteAsync>d__15.MoveNext() в D:\\a\\_work\\1\\s\\src\\Microsoft.Docker\\DockerComposeClient.cs:строка 287\r\n--- Конец трассировка стека из предыдущего расположения, где возникло исключение ---\r\n   в System.Runtime.CompilerServices.TaskAwaiter.ThrowForNonSuccess(Task task)\r\n   в System.Runtime.CompilerServices.TaskAwaiter.HandleNonSuccessAndDebuggerNotification(Task task)\r\n   в Microsoft.Docker.DockerComposeClient.<DownAsync>d__8.MoveNext() в D:\\a\\_work\\1\\s\\src\\Microsoft.Docker\\DockerComposeClient.cs:строка 120\r\n--- Конец трассировка стека из предыдущего расположения, где возникло исключение ---\r\n   в System.Runtime.CompilerServices.TaskAwaiter.ThrowForNonSuccess(Task task)\r\n   в System.Runtime.CompilerServices.TaskAwaiter.HandleNonSuccessAndDebuggerNotification(Task task)\r\n   в Microsoft.Docker.DockerWorkspace.<ComposeDownContainersAsync>d__33.MoveNext() в D:\\a\\_work\\1\\s\\src\\Microsoft.Docker\\DockerWorkspace.cs:строка 446\r\n--- Конец трассировка стека из предыдущего расположения, где возникло исключение ---\r\n   в System.Runtime.CompilerServices.TaskAwaiter.ThrowForNonSuccess(Task task)\r\n   в System.Runtime.CompilerServices.TaskAwaiter.HandleNonSuccessAndDebuggerNotification(Task task)\r\n   в Microsoft.Docker.BuildTasks.ComposeDownContainers.<ExecuteCoreAsync>d__4.MoveNext() в D:\\a\\_work\\1\\s\\src\\Microsoft.Docker.BuildTasks\\ComposeDownContainers.cs:строка 16\r\n--- Конец трассировка стека из предыдущего расположения, где возникло исключение ---\r\n   в System.Runtime.CompilerServices.TaskAwaiter.ThrowForNonSuccess(Task task)\r\n   в System.Runtime.CompilerServices.TaskAwaiter.HandleNonSuccessAndDebuggerNotification(Task task)\r\n   в Microsoft.Docker.BuildTasks.DockerBuildTask.<ExecuteAsync>d__34.MoveNext() в D:\\a\\_work\\1\\s\\src\\Microsoft.Docker.BuildTasks\\DockerBuildTask.cs:строка 82","ContainerToolsException.HResult":"-2146233088","ContainerToolsException.CommandLine.Program":"docker-compose","ContainerToolsException.CommandLine.TelemetrySafeArguments":"","ContainerToolsException.CommandLine.ExitCode":"1","ContainerToolsException.CommandLine.ErrorOutput":".FileNotFoundError: [Errno 2] No such file or directory: 'C:\\\\Temp\\\\Gateway\\\\docker-compose.yml'"},{"ContainerToolsException.Message":".FileNotFoundError: [Errno 2] No such file or directory: 'C:\\\\Temp\\\\Gateway\\\\docker-compose.yml'","ContainerToolsException.ErrorCode":"DT1001","ContainerToolsException.StackTrace":"   в System.Runtime.CompilerServices.TaskAwaiter.ThrowForNonSuccess(Task task)\r\n   в System.Runtime.CompilerServices.TaskAwaiter.HandleNonSuccessAndDebuggerNotification(Task task)\r\n   в Microsoft.Docker.DockerComposeClient.<ExecuteAsync>d__15.MoveNext() в D:\\a\\_work\\1\\s\\src\\Microsoft.Docker\\DockerComposeClient.cs:строка 287\r\n--- Конец трассировка стека из предыдущего расположения, где возникло исключение ---\r\n   в System.Runtime.CompilerServices.TaskAwaiter.ThrowForNonSuccess(Task task)\r\n   в System.Runtime.CompilerServices.TaskAwaiter.HandleNonSuccessAndDebuggerNotification(Task task)\r\n   в Microsoft.Docker.DockerComposeClient.<DownAsync>d__8.MoveNext() в D:\\a\\_work\\1\\s\\src\\Microsoft.Docker\\DockerComposeClient.cs:строка 120\r\n--- Конец трассировка стека из предыдущего расположения, где возникло исключение ---\r\n   в System.Runtime.CompilerServices.TaskAwaiter.ThrowForNonSuccess(Task task)\r\n   в System.Runtime.CompilerServices.TaskAwaiter.HandleNonSuccessAndDebuggerNotification(Task task)\r\n   в Microsoft.Docker.DockerWorkspace.<ComposeDownContainersAsync>d__33.MoveNext() в D:\\a\\_work\\1\\s\\src\\Microsoft.Docker\\DockerWorkspace.cs:строка 445\r\n--- Конец трассировка стека из предыдущего расположения, где возникло исключение ---\r\n   в System.Runtime.CompilerServices.TaskAwaiter.ThrowForNonSuccess(Task task)\r\n   в System.Runtime.CompilerServices.TaskAwaiter.HandleNonSuccessAndDebuggerNotification(Task task)\r\n   в Microsoft.Docker.BuildTasks.ComposeDownContainers.<ExecuteCoreAsync>d__4.MoveNext() в D:\\a\\_work\\1\\s\\src\\Microsoft.Docker.BuildTasks\\ComposeDownContainers.cs:строка 16\r\n--- Конец трассировка стека из предыдущего расположения, где возникло исключение ---\r\n   в System.Runtime.CompilerServices.TaskAwaiter.ThrowForNonSuccess(Task task)\r\n   в System.Runtime.CompilerServices.TaskAwaiter.HandleNonSuccessAndDebuggerNotification(Task task)\r\n   в Microsoft.Docker.BuildTasks.DockerBuildTask.<ExecuteAsync>d__34.MoveNext() в D:\\a\\_work\\1\\s\\src\\Microsoft.Docker.BuildTasks\\DockerBuildTask.cs:строка 82","ContainerToolsException.HResult":"-2146233088","ContainerToolsException.CommandLine.Program":"docker-compose","ContainerToolsException.CommandLine.TelemetrySafeArguments":"","ContainerToolsException.CommandLine.ExitCode":"1","ContainerToolsException.CommandLine.ErrorOutput":".FileNotFoundError: [Errno 2] No such file or directory: 'C:\\\\Temp\\\\Gateway\\\\docker-compose.yml'"}]